django_universal_view_decorator/__init__.py
django_universal_view_decorator/five.py
django_universal_view_decorator/utils.py
django_universal_view_decorator/decorators/__init__.py
django_universal_view_decorator/decorators/universal_view_decorator.py
django_universal_view_decorator/decorators/view_class_decorator.py
django_universal_view_decorator/decorators/view_decorator_base.py
django_universal_view_decorator/decorators/view_routine_decorator.py
django_universal_view_decorator-0.1.0.dist-info/DESCRIPTION.rst
django_universal_view_decorator-0.1.0.dist-info/METADATA
django_universal_view_decorator-0.1.0.dist-info/RECORD
django_universal_view_decorator-0.1.0.dist-info/WHEEL
django_universal_view_decorator-0.1.0.dist-info/metadata.json
django_universal_view_decorator-0.1.0.dist-info/top_level.txt
