Metadata-Version: 2.0
Name: django-universal-view-decorator
Version: 0.1.0
Summary: Smart view class (CBV) decoration
Home-page: https://github.com/pasztorpisti/django-universal-view-decorator
Author: István Pásztor
Author-email: pasztorpisti@gmail.com
License: MIT
Keywords: django universal view class decorator
Platform: UNKNOWN
Classifier: License :: OSI Approved :: MIT License
Classifier: Development Status :: 5 - Production/Stable
Classifier: Intended Audience :: Developers
Classifier: Topic :: Software Development :: Libraries :: Python Modules
Classifier: Framework :: Django
Classifier: Programming Language :: Python :: 2
Classifier: Programming Language :: Python :: 3
Classifier: Programming Language :: Python :: Implementation :: CPython
Classifier: Programming Language :: Python :: Implementation :: PyPy
